Metadata-Version: 2.1
Name: NumIntM
Version: 0.0.2
Summary: Numerical integration using methods like: Trapezoidal method, Simpson rule, Newton cotes method and Compound trapezoidal method 
Home-page: 
Author: Emmanuel Martínez
Author-email: 
License: MIT
Keywords: numerical integration aproximation
Classifier: Development Status :: 6 - Mature
Classifier: Intended Audience :: Education
Classifier: Operating System :: Microsoft :: Windows :: Windows 10
Classifier: Natural Language :: Spanish
Classifier: License :: OSI Approved :: MIT License
Classifier: Programming Language :: Python :: 3.9
Classifier: Topic :: Scientific/Engineering :: Mathematics
License-File: LICENCE.txt
